cfgformalizer/__init__.py
cfgformalizer/cisco/cisco.py
cfgformalizer/cisco/statement.py
cfgformalizer/command_line.py
cfgformalizer/decorators.py
cfgformalizer/stanza.py
cfgformalizer/statement.py
cfgformalizer-0.1.0.dist-info/entry_points.txt
cfgformalizer-0.1.0.dist-info/WHEEL
cfgformalizer-0.1.0.dist-info/METADATA
cfgformalizer-0.1.0.dist-info/RECORD
